everviz/__init__.py
everviz/config.py
everviz/everest_hooks.py
everviz/log.py
everviz/util.py
everviz/version.py
everviz/assets/axis_customization.css
everviz/components/__init__.py
everviz/components/list_select.py
everviz/data/__init__.py
everviz/data/load_csv/__init__.py
everviz/data/load_csv/get_data.py
everviz/pages/__init__.py
everviz/pages/configuration.py
everviz/pages/controls.py
everviz/pages/crossplot.py
everviz/pages/deltaplot.py
everviz/pages/gradientplot.py
everviz/pages/objectives.py
everviz/pages/summary_values.py
everviz/pages/wells_values.py
everviz/plugins/__init__.py
everviz/plugins/gradient_plot.py
everviz/plugins/plugin_abc.py
everviz/plugins/best_controls_plot/__init__.py
everviz/plugins/best_controls_plot/best_controls_plot.py
everviz/plugins/config_editor/__init__.py
everviz/plugins/config_editor/config_editor.py
everviz/plugins/controls_plot/__init__.py
everviz/plugins/controls_plot/controls_plot.py
everviz/plugins/crossplot/__init__.py
everviz/plugins/crossplot/crossplot.py
everviz/plugins/crossplot/crossplot_indexed.py
everviz/plugins/crossplot/callback/__init__.py
everviz/plugins/crossplot/callback/crossplot_callback.py
everviz/plugins/crossplot/callback/crossplot_indexed_dropdown.py
everviz/plugins/delta_plot/__init__.py
everviz/plugins/delta_plot/delta_plot.py
everviz/plugins/objectives_plot/__init__.py
everviz/plugins/objectives_plot/objectives_plot.py
everviz/plugins/objectives_plot/single_objectives_plot.py
everviz/plugins/objectives_plot/util.py
everviz/plugins/summary_plot/__init__.py
everviz/plugins/summary_plot/summary_callback.py
everviz/plugins/summary_plot/summary_plot.py
everviz/plugins/summary_plot/util.py
everviz/plugins/summary_plot/wells_plot.py
everviz/plugins/utils/__init__.py
everviz/plugins/utils/layout/__init__.py
everviz/plugins/utils/layout/sidebar_layout.py
everviz-0.1.2.dist-info/licenses/LICENSE
everviz-0.1.2.dist-info/METADATA
everviz-0.1.2.dist-info/WHEEL
everviz-0.1.2.dist-info/entry_points.txt
everviz-0.1.2.dist-info/top_level.txt
everviz-0.1.2.dist-info/RECORD
