Metadata-Version: 2.4
Name: everviz
Version: 0.1.2
Summary: Visualization for Everest
Author-email: Equinor ASA <fg_sib-scout@equinor.com>
License: AGPL-3.0
Project-URL: repository, https://github.com/equinor/everviz
Classifier: Environment :: Plugins
Classifier: Intended Audience :: Developers
Classifier: Intended Audience :: Science/Research
Classifier: License :: OSI Approved :: GNU Affero General Public License v3
Classifier: Natural Language :: English
Classifier: Programming Language :: Python
Classifier: Programming Language :: Python :: 3.8
Classifier: Programming Language :: Python :: 3.9
Classifier: Programming Language :: Python :: 3.10
Classifier: Programming Language :: Python :: 3.11
Classifier: Programming Language :: Python :: 3.12
Classifier: Topic :: Scientific/Engineering
Classifier: Topic :: Software Development :: Libraries :: Python Modules
License-File: LICENSE
Requires-Dist: pyyaml
Requires-Dist: pandas
Requires-Dist: numpy
Requires-Dist: dash>=2.0
Requires-Dist: webviz-config>=0.2.0
Requires-Dist: webviz-config-equinor
Requires-Dist: plotly
Requires-Dist: flask
Provides-Extra: test
Requires-Dist: dash[testing]; extra == "test"
Requires-Dist: pillow; extra == "test"
Requires-Dist: pytest-mock; extra == "test"
Requires-Dist: sphinx; extra == "test"
Requires-Dist: polars; extra == "test"
Provides-Extra: style
Requires-Dist: pre-commit; extra == "style"
Dynamic: license-file
